{
  "id": 4687,
  "questions": [{
    "id": 6526,
    "questionText": "\"A very small man can cast a very large shadow\"",
    "maxTries": 3,
    "answers": [{
      "id": 17271,
      "questionId": 6526,
      "answerDesc": "Roose Bolton",
      "correctAnswer" : false
    }, {
      "id": 17272,
      "questionId": 6526,
      "answerDesc": "Lord Varys",
      "correctAnswer" : true
    }, {
      "id": 17273,
      "questionId": 6526,
      "answerDesc": "Tywin Lanister",
      "correctAnswer" : false
    }, {
      "id": 27337,
      "questionId": 6526,
      "answerDesc": "Lord Baelish",
      "correctAnswer" : true
    }, {
      "id": 27337,
      "questionId": 6526,
      "answerDesc": "Ned Stark",
      "correctAnswer" : false
    }]
  },
    {
      "id": 6526,
      "questionText": "\"The more people you live the weaker you are\"",
      "maxTries": 3,
      "answers": [{
        "id": 17271,
        "questionId": 6526,
        "answerDesc": "Cersei Lanister",
        "correctAnswer" : true
      }, {
        "id": 17272,
        "questionId": 6526,
        "answerDesc": "Daenerys Targaryen",
        "correctAnswer" : false
      }, {
        "id": 17273,
        "questionId": 6526,
        "answerDesc": "Jon Snow",
        "correctAnswer" : false
      }, {
        "id": 27337,
        "questionId": 6526,
        "answerDesc": "Ygritte",
        "correctAnswer" : false
      }, {
        "id": 27337,
        "questionId": 6526,
        "answerDesc": "Lord Baelish",
        "correctAnswer" : false
      }]
    },
    {
      "id": 6526,
      "questionText": "\"I'm not going to stop the wheel. I'm going to break the wheel\"",
      "maxTries": 3,
      "answers": [{
        "id": 17271,
        "questionId": 6526,
        "answerDesc": "Walder Fray",
        "correctAnswer" : false
      }, {
        "id": 17272,
        "questionId": 6526,
        "answerDesc": "Balon Greyjoy",
        "correctAnswer" : false
      }, {
        "id": 17273,
        "questionId": 6526,
        "answerDesc": "Robb Stark",
        "correctAnswer" : false
      }, {
        "id": 27337,
        "questionId": 6526,
        "answerDesc": "Stanis Baratheon",
        "correctAnswer" : false
      }, {
        "id": 27337,
        "questionId": 6526,
        "answerDesc": "Daenerys Targaryen",
        "correctAnswer" : true
      }]
    }]
}